time_on_fire/__init__.py
time_on_fire/activities.db
time_on_fire/cli.py
time_on_fire/config.py
time_on_fire/report.py
time_on_fire/track.py
time_on_fire-0.1.1.dist-info/LICENSE
time_on_fire-0.1.1.dist-info/METADATA
time_on_fire-0.1.1.dist-info/WHEEL
time_on_fire-0.1.1.dist-info/entry_points.txt
time_on_fire-0.1.1.dist-info/top_level.txt
time_on_fire-0.1.1.dist-info/RECORD
