Metadata-Version: 2.1
Name: time-on-fire
Version: 0.1.1
Summary: A simple activity tracker for Windows.
Home-page: UNKNOWN
Author: zapvolt
Author-email: ag11012008@gmail.com
License: GNU GPLv3
Keywords: python time-tracking time tracking monitoring report
Platform: UNKNOWN
Classifier: Development Status :: 4 - Beta
Classifier: License :: OSI Approved :: GNU General Public License (GPL)
Classifier: Intended Audience :: End Users/Desktop
Classifier: Programming Language :: Python :: 3
Classifier: Operating System :: Microsoft :: Windows
License-File: LICENSE
Requires-Dist: click
Requires-Dist: pywin32
Requires-Dist: psutil
Requires-Dist: tabulate
